AUTHORS
CHANGES.rst
CONTRIBUTING.rst
LICENSE
MANIFEST.in
README.rst
setup.cfg
setup.py
tox.ini
qingmi/__about__.py
qingmi/__init__.py
qingmi/cli.py
qingmi.egg-info/PKG-INFO
qingmi.egg-info/SOURCES.txt
qingmi.egg-info/dependency_links.txt
qingmi.egg-info/entry_points.txt
qingmi.egg-info/not-zip-safe
qingmi.egg-info/requires.txt
qingmi.egg-info/top_level.txt
qingmi/admin/__init__.py
qingmi/api/__init__.py
qingmi/config/__init__.py
qingmi/deploy/__init__.py
qingmi/helper/__init__.py
qingmi/lib/__init__.py
qingmi/model/__init__.py
qingmi/oauth/__init__.py
qingmi/script/__init__.py
qingmi/test/__init__.py