Metadata-Version: 2.1
Name: qingmi
Version: 0.1.1
Summary: Common modules and toolsets for rapid and efficient development of flask Web.
Home-page: https://www.zhuxiongxian.cc
Author: zhuxiongxian
Author-email: zhuxiongxian@gmail.com
License: BSD
Project-URL: Source, https://github.com/xiongxianzhu/qingmi
Keywords: qingmi,flask
Platform: any
Classifier: Framework :: Flask
Classifier: Development Status :: 1 - Planning
Classifier: Environment :: Web Environment
Classifier: Intended Audience :: Developers
Classifier: License :: OSI Approved :: BSD License
Classifier: Operating System :: OS Independent
Classifier: Programming Language :: Python
Classifier: Programming Language :: Python :: 3
Classifier: Programming Language :: Python :: 3.6
Classifier: Topic :: Internet :: WWW/HTTP
Classifier: Topic :: Internet :: WWW/HTTP :: Dynamic Content
Classifier: Topic :: Software Development :: Libraries :: Application Frameworks
Classifier: Topic :: Software Development :: Libraries :: Python Modules
Provides-Extra: testing
Provides-Extra: bcrypt
